rmyc_bridge/__init__.py
rmyc_bridge/blaster.py
rmyc_bridge/chassis.py
rmyc_bridge/game_msg.py
rmyc_bridge/gimbal.py
rmyc_bridge/robot.py
rmyc_bridge/sdk.py
rmyc_bridge/serial.py
rmyc_bridge-0.1.dist-info/licenses/LICENSE
rmyc_bridge-0.1.dist-info/METADATA
rmyc_bridge-0.1.dist-info/WHEEL
rmyc_bridge-0.1.dist-info/top_level.txt
rmyc_bridge-0.1.dist-info/RECORD
