Metadata-Version: 2.4
Name: rmyc_bridge
Version: 0.1
Summary: A bridge for RMYC to connect with other systems
Author: n1ghts4kura
Author-email: 1825259836@qq.com
License-File: LICENSE
Requires-Dist: pyserial
Dynamic: author
Dynamic: author-email
Dynamic: license-file
Dynamic: requires-dist
Dynamic: summary
